tinyevolver/__init__.py
tinyevolver/core.py
tinyevolver/island.py
tinyevolver-0.1.dist-info/DESCRIPTION.rst
tinyevolver-0.1.dist-info/METADATA
tinyevolver-0.1.dist-info/RECORD
tinyevolver-0.1.dist-info/WHEEL
tinyevolver-0.1.dist-info/metadata.json
tinyevolver-0.1.dist-info/top_level.txt
