Metadata-Version: 2.0
Name: tinyevolver
Version: 0.1
Summary: A simple, tiny engine for creating genetic algorithms.
Home-page: https://github.com/olliemath/Python-TinyEvolver/
Author: Oliver Margetts
Author-email: oliver.margetts@gmail.com
License: GNU GPL V.2
Keywords: genetic,evolutionary,algorithms,optimization
Platform: UNKNOWN
Classifier: Development Status :: 4 - Beta
Classifier: Intended Audience :: Scientists
Classifier: Intended Audience :: Developers
Classifier: Topic :: Software DevelopmentTopic :: Genetic Algorithms
Classifier: Topic :: Optimization
Classifier: Topic :: Modelling
Classifier: License :: OSI Approved :: GNU GPL V.2
Classifier: Programming Language :: Python :: 2
Classifier: Programming Language :: Python :: 2.6
Classifier: Programming Language :: Python :: 2.7
Classifier: Programming Language :: Python :: 3
Classifier: Programming Language :: Python :: 3.4
Classifier: Programming Language :: Python :: 3.5
Classifier: Programming Language :: Python :: Implementation :: CPythonProgramming Language :: Python :: Implementation :: PyPy
